constellatus/__init__.py
constellatus/__main__.py
constellatus/constellatus.py
constellatus-0.0.2.dist-info/METADATA
constellatus-0.0.2.dist-info/WHEEL
constellatus-0.0.2.dist-info/entry_points.txt
constellatus-0.0.2.dist-info/top_level.txt
constellatus-0.0.2.dist-info/RECORD
