Metadata-Version: 2.1
Name: constellatus
Version: 0.0.2
Summary: Elder data composition
Home-page: https://github.com/constellatus/constellatus
Author: eons
Author-email: support@eons.llc
Project-URL: Bug Tracker, https://github.com/constellatus/constellatus/issues
Classifier: Programming Language :: Python :: 3
Classifier: License :: OSI Approved :: MIT License
Classifier: Operating System :: OS Independent
Classifier: Development Status :: 4 - Beta
Requires-Python: >=3.7
Requires-Dist: apie
Requires-Dist: flask
Requires-Dist: eons
